eeg_templates/__init__.py
eeg_templates/ep_template.py
experiment_gui/__init__.py
experiment_gui/json_parser.py
experiment_gui/main.py
experiment_gui/screen.py
pf_2023b_neural_decoding-0.0.13.dist-info/METADATA
pf_2023b_neural_decoding-0.0.13.dist-info/WHEEL
pf_2023b_neural_decoding-0.0.13.dist-info/top_level.txt
pf_2023b_neural_decoding-0.0.13.dist-info/RECORD
